ragelo/__init__.py
ragelo/__main__.py
ragelo/logger.py
ragelo/utils.py
ragelo/agent_rankers/__init__.py
ragelo/agent_rankers/base_agent_ranker.py
ragelo/agent_rankers/elo_ranker.py
ragelo/cli/__init__.py
ragelo/cli/answer_evaluators_cli.py
ragelo/cli/args.py
ragelo/cli/cli.py
ragelo/cli/retrieval_evaluator_cli.py
ragelo/cli/utils.py
ragelo/evaluators/__init__.py
ragelo/evaluators/base_evaluator.py
ragelo/evaluators/answer_evaluators/__init__.py
ragelo/evaluators/answer_evaluators/base_answer_evaluator.py
ragelo/evaluators/answer_evaluators/chat_pairwise_evaluator.py
ragelo/evaluators/answer_evaluators/custom_pairwise_evaluator.py
ragelo/evaluators/answer_evaluators/custom_prompt_evaluator.py
ragelo/evaluators/answer_evaluators/domain_expert_evaluator.py
ragelo/evaluators/answer_evaluators/pairwise_evaluator.py
ragelo/evaluators/retrieval_evaluators/__init__.py
ragelo/evaluators/retrieval_evaluators/base_retrieval_evaluator.py
ragelo/evaluators/retrieval_evaluators/custom_prompt_evaluator.py
ragelo/evaluators/retrieval_evaluators/domain_expert_evaluator.py
ragelo/evaluators/retrieval_evaluators/few_shot_evaluator.py
ragelo/evaluators/retrieval_evaluators/rdnam_evaluator.py
ragelo/evaluators/retrieval_evaluators/reasoner_evaluator.py
ragelo/llm_providers/__init__.py
ragelo/llm_providers/base_llm_provider.py
ragelo/llm_providers/ollama_client.py
ragelo/llm_providers/openai_client.py
ragelo/types/__init__.py
ragelo/types/answer_formats.py
ragelo/types/evaluables.py
ragelo/types/experiment.py
ragelo/types/formats.py
ragelo/types/query.py
ragelo/types/results.py
ragelo/types/types.py
ragelo/types/configurations/__init__.py
ragelo/types/configurations/agent_ranker_configs.py
ragelo/types/configurations/answer_evaluator_configs.py
ragelo/types/configurations/base_configs.py
ragelo/types/configurations/cli_configs.py
ragelo/types/configurations/llm_provider_configs.py
ragelo/types/configurations/retrieval_evaluator_configs.py
ragelo-0.3.1.dist-info/licenses/LICENSE
tests/conftest.py
tests/cli/test_cli.py
ragelo-0.3.1.dist-info/METADATA
ragelo-0.3.1.dist-info/WHEEL
ragelo-0.3.1.dist-info/entry_points.txt
ragelo-0.3.1.dist-info/top_level.txt
ragelo-0.3.1.dist-info/RECORD
