Metadata-Version: 2.4
Name: ragelo
Version: 0.3.1
Summary: RAGElo: A Tool for Evaluating Retrieval-Augmented Generation Models
Author-email: Zeta Alpha <support@zeta-alpha.com>, Arthur Câmara <camara@zeta-alpha.com>
License: Apache-2.0
Project-URL: Homepage, https://github.com/zetaalphavector/RAGElo
Project-URL: Repository, https://github.com/zetaalphavector/RAGElo
Classifier: Development Status :: 2 - Pre-Alpha
Classifier: Environment :: Console
Classifier: Intended Audience :: Developers
Classifier: Intended Audience :: Science/Research
Classifier: License :: OSI Approved :: Apache Software License
Classifier: Programming Language :: Python :: 3.12
Classifier: Topic :: Scientific/Engineering :: Artificial Intelligence
Classifier: Topic :: Software Development :: Libraries :: Python Modules
Classifier: Topic :: System :: Benchmark
Requires-Python: >=3.8
License-File: LICENSE
Requires-Dist: openai>=1.78.0
Requires-Dist: tenacity<9.0.0
Requires-Dist: typer>=0.16.0
Requires-Dist: numpy>=1.24
Requires-Dist: pydantic>=2.0
Requires-Dist: eval-type-backport>=0.2.0
Requires-Dist: typing_extensions>=4.0.0; python_version < "3.11"
Requires-Dist: jinja2>=3.1.0
Provides-Extra: eval
Requires-Dist: ir-measures>=0.3.4; extra == "eval"
Dynamic: license-file
